synapse/__init__.py
synapse/async.py
synapse/axon.py
synapse/common.py
synapse/compat.py
synapse/cortex.py
synapse/crypto.py
synapse/daemon.py
synapse/datamodel.py
synapse/datfile.py
synapse/dyndeps.py
synapse/eventbus.py
synapse/exc.py
synapse/glob.py
synapse/hivemind.py
synapse/impulse.py
synapse/link.py
synapse/mindmeld.py
synapse/neuron.py
synapse/reactor.py
synapse/statemach.py
synapse/telepath.py
synapse/cores/__init__.py
synapse/cores/common.py
synapse/cores/postgres.py
synapse/cores/ram.py
synapse/cores/sqlite.py
synapse/lib/__init__.py
synapse/lib/atomfile.py
synapse/lib/atomic.py
synapse/lib/cache.py
synapse/lib/cli.py
synapse/lib/heap.py
synapse/lib/moddef.py
synapse/lib/persist.py
synapse/lib/pki.py
synapse/lib/plugins.py
synapse/lib/queue.py
synapse/lib/ratelimit.py
synapse/lib/sched.py
synapse/lib/service.py
synapse/lib/session.py
synapse/lib/socket.py
synapse/lib/tags.py
synapse/lib/thishost.py
synapse/lib/thisplat.py
synapse/lib/threads.py
synapse/lib/types.py
synapse/lib/urlhelp.py
synapse/lib/userauth.py
synapse/lib/webapp.py
synapse/lib/webdav.py
synapse/lib/platforms/__init__.py
synapse/lib/platforms/common.py
synapse/lib/platforms/darwin.py
synapse/lib/platforms/freebsd.py
synapse/lib/platforms/linux.py
synapse/lib/platforms/windows.py
synapse/links/__init__.py
synapse/links/common.py
synapse/links/local.py
synapse/links/ssh.py
synapse/links/ssl.py
synapse/links/tcp.py
synapse/swarm/__init__.py
synapse/swarm/runtime.py
synapse/swarm/syntax.py
synapse/swarm/opers/__init__.py
synapse/swarm/opers/basic.py
synapse/swarm/opers/common.py
synapse/tools/__init__.py
synapse/tools/dmon.py
synapse/tools/droned.py
synapse/tools/easycert.py
synapse/tools/httpd.py
synapse/tools/melder.py
synapse/tools/neuron.py
synapse/tools/neutool.py
synapse/tools/pkitool.py
synapse/tools/queend.py
synapse/tools/server.py
synapse/tools/worker.py
viv_synapse-0.0.7.dist-info/DESCRIPTION.rst
viv_synapse-0.0.7.dist-info/METADATA
viv_synapse-0.0.7.dist-info/RECORD
viv_synapse-0.0.7.dist-info/WHEEL
viv_synapse-0.0.7.dist-info/metadata.json
viv_synapse-0.0.7.dist-info/top_level.txt
