Metadata-Version: 2.0
Name: viv-synapse
Version: 0.0.7
Summary: Synapse Distributed Computing Framework
Home-page: https://github.com/vivisect/synapse
Author: Invisigoth Kenshoto
Author-email: invisigoth.kenshoto@gmail.com
License: Apache License 2.0
Platform: UNKNOWN
Classifier: Development Status :: 4 - Beta
Classifier: License :: OSI Approved :: Apache Software License
Classifier: Topic :: System :: Clustering
Classifier: Topic :: System :: Distributed Computing
Classifier: Topic :: System :: Software Distribution
Requires-Dist: requests
Requires-Dist: tornado (>=3.2)
Requires-Dist: cryptography (>=1.1.2)
Requires-Dist: msgpack-python (>=0.4.2)
